{
  "description": "A list of ClusterRoleBinding objects. *DEPRECATED* in v1.17 in favor of `\"rbac.authorization.k8s.io/v1\"` ClusterRoleBindingList, and will no longer be served in v1.22.",
  "properties": {
    "apiVersion": {
      "description": "The version of the schema for the object representation",
      "enum": [
        "rbac.authorization.k8s.io/v1alpha1"
      ],
      "type": "string"
    },
    "items": {
      "description": "A list of ClusterRoleBinding objects",
      "items": {
        "$ref": "#/definitions/io.k8s.api.rbac.v1alpha1.ClusterRoleBinding.GET"
      },
      "type": "array"
    },
    "kind": {
      "description": "A string value representing the REST resource",
      "enum": [
        "ClusterRoleBindingList"
      ],
      "type": "string"
    },
    "metadata": {
      "$ref": "#/definitions/io.k8s.apimachinery.pkg.apis.meta.v1.ListMeta",
      "description": "Standard list metadata"
    }
  },
  "required": [
    "apiVersion",
    "items",
    "kind",
    "metadata"
  ],
  "type": "object",
  "x-kubernetes-group-version-kind": [
    {
      "group": "rbac.authorization.k8s.io",
      "kind": "ClusterRoleBindingList",
      "version": "v1alpha1"
    }
  ]
}
