{
  "consumes": [
    "*/*"
  ],
  "description": "replace the specified ControllerRevision",
  "operationId": "replaceAppsV1beta1NamespacedControllerRevision",
  "parameters": [
    {
      "in": "body",
      "name": "body",
      "required": true,
      "schema": {
        "$ref": "#/definitions/io.k8s.api.apps.v1beta1.ControllerRevision.UPDATE"
      }
    },
    {
      "$ref": "#/parameters/dryRun"
    },
    {
      "$ref": "#/parameters/fieldManager"
    },
    {
      "description": "name of the ControllerRevision",
      "in": "path",
      "name": "name",
      "required": true,
      "type": "string",
      "uniqueItems": true
    },
    {
      "$ref": "#/parameters/namespace"
    },
    {
      "$ref": "#/parameters/pretty"
    }
  ],
  "path": "/apis/apps/v1beta1/namespaces/{namespace}/controllerrevisions/{name}",
  "produces": [
    "application/json",
    "application/yaml",
    "application/vnd.kubernetes.protobuf"
  ],
  "responses": {
    "200": {
      "description": "OK",
      "schema": {
        "$ref": "#/definitions/io.k8s.api.apps.v1beta1.ControllerRevision.GET"
      }
    },
    "201": {
      "description": "Created",
      "schema": {
        "$ref": "#/definitions/io.k8s.api.apps.v1beta1.ControllerRevision.GET"
      }
    },
    "401": {
      "description": "Unauthorized"
    }
  },
  "schemes": [
    "https"
  ],
  "tags": [
    "apps_v1beta1"
  ],
  "verb": "put",
  "x-kubernetes-action": "put",
  "x-kubernetes-group-version-kind": {
    "group": "apps",
    "kind": "ControllerRevision",
    "version": "v1beta1"
  }
}
