{
  "consumes": [
    "*/*"
  ],
  "description": "read the specified ResourceClaimTemplate",
  "operationId": "readResourceV1beta1NamespacedResourceClaimTemplate",
  "parameters": [
    {
      "description": "name of the ResourceClaimTemplate",
      "in": "path",
      "name": "name",
      "required": true,
      "type": "string",
      "uniqueItems": true
    },
    {
      "$ref": "#/parameters/namespace"
    },
    {
      "$ref": "#/parameters/pretty"
    }
  ],
  "path": "/apis/resource.k8s.io/v1beta1/namespaces/{namespace}/resourceclaimtemplates/{name}",
  "produces": [
    "application/json",
    "application/yaml",
    "application/vnd.kubernetes.protobuf",
    "application/cbor"
  ],
  "responses": {
    "200": {
      "description": "OK",
      "schema": {
        "$ref": "#/definitions/io.k8s.api.resource.v1beta1.ResourceClaimTemplate"
      }
    },
    "401": {
      "description": "Unauthorized"
    }
  },
  "schemes": [
    "https"
  ],
  "tags": [
    "resource_v1beta1"
  ],
  "verb": "get",
  "x-kubernetes-action": "get",
  "x-kubernetes-group-version-kind": {
    "group": "resource.k8s.io",
    "kind": "ResourceClaimTemplate",
    "version": "v1beta1"
  }
}