{
  "consumes": [
    "*/*"
  ],
  "description": "create a HorizontalPodAutoscaler",
  "operationId": "createAutoscalingV2beta1NamespacedHorizontalPodAutoscaler",
  "parameters": [
    {
      "in": "body",
      "name": "body",
      "required": true,
      "schema": {
        "$ref": "#/definitions/io.k8s.api.autoscaling.v2beta1.HorizontalPodAutoscaler"
      }
    },
    {
      "$ref": "#/parameters/dryRun"
    },
    {
      "$ref": "#/parameters/fieldManager"
    },
    {
      "description": "fieldValidation determines how the server should respond to unknown/duplicate fields in the object in the request. Introduced as alpha in 1.23, older servers or servers with the `ServerSideFieldValidation` feature disabled will discard valid values specified in  this param and not perform any server side field validation. Valid values are: - Ignore: ignores unknown/duplicate fields. - Warn: responds with a warning for each unknown/duplicate field, but successfully serves the request. - Strict: fails the request on unknown/duplicate fields.",
      "in": "query",
      "name": "fieldValidation",
      "type": "string",
      "uniqueItems": true
    },
    {
      "$ref": "#/parameters/namespace"
    }
  ],
  "path": "/apis/autoscaling/v2beta1/namespaces/{namespace}/horizontalpodautoscalers",
  "produces": [
    "application/json",
    "application/yaml",
    "application/vnd.kubernetes.protobuf"
  ],
  "responses": {
    "200": {
      "description": "OK",
      "schema": {
        "$ref": "#/definitions/io.k8s.api.autoscaling.v2beta1.HorizontalPodAutoscaler"
      }
    },
    "201": {
      "description": "Created",
      "schema": {
        "$ref": "#/definitions/io.k8s.api.autoscaling.v2beta1.HorizontalPodAutoscaler"
      }
    },
    "202": {
      "description": "Accepted",
      "schema": {
        "$ref": "#/definitions/io.k8s.api.autoscaling.v2beta1.HorizontalPodAutoscaler"
      }
    },
    "401": {
      "description": "Unauthorized"
    }
  },
  "schemes": [
    "https"
  ],
  "tags": [
    "autoscaling_v2beta1"
  ],
  "verb": "post",
  "x-kubernetes-action": "post",
  "x-kubernetes-group-version-kind": {
    "group": "autoscaling",
    "kind": "HorizontalPodAutoscaler",
    "version": "v2beta1"
  }
}